{"trial_id": "3", "hyperparameters": {"space": [{"class_name": "Int", "config": {"name": "shree_units", "default": null, "conditions": [], "min_value": 8, "max_value": 128, "step": 1, "sampling": "linear"}}], "values": {"shree_units": 92}}, "metrics": {"metrics": {"loss": {"direction": "min", "observations": [{"value": [0.5044932961463928], "step": 3}]}, "accuracy": {"direction": "max", "observations": [{"value": [0.7801302671432495], "step": 3}]}, "val_loss": {"direction": "min", "observations": [{"value": [0.5004819631576538], "step": 3}]}, "val_accuracy": {"direction": "max", "observations": [{"value": [0.798701286315918], "step": 3}]}, "multi_objective": {"direction": "min", "observations": [{"value": [-0.798701286315918], "step": 3}]}}}, "score": -0.798701286315918, "best_step": 3, "status": "COMPLETED", "message": null}